ThreadedFileLoader/ThreadedFileLoader.py
ThreadedFileLoader/__init__.py
ThreadedFileLoader/__main__.py
ThreadedFileLoader-1.0.0.11.dist-info/METADATA
ThreadedFileLoader-1.0.0.11.dist-info/WHEEL
ThreadedFileLoader-1.0.0.11.dist-info/top_level.txt
ThreadedFileLoader-1.0.0.11.dist-info/RECORD
