Metadata-Version: 2.1
Name: ThreadedFileLoader
Version: 1.0.0.11
Summary: UNKNOWN
Home-page: https://QuantumNovice.github.io/ThreadedFileLoader
Author: QuantumNovice
Author-email: portabl3lapy@gmail.com
License: MIT
Platform: UNKNOWN
Classifier: License :: OSI Approved :: MIT License
Classifier: Programming Language :: Python :: 3
Classifier: Programming Language :: Python :: 3.7
Requires-Python: >=3.6
Requires-Dist: imageio
Requires-Dist: wheel
